example/app.py
ttbot/__init__.py
ttbot/client.py
ttbot/py.typed
ttbot/server.py
ttbot/types.py
ttbotlib-0.13.dist-info/LICENSE.md
ttbotlib-0.13.dist-info/METADATA
ttbotlib-0.13.dist-info/WHEEL
ttbotlib-0.13.dist-info/top_level.txt
ttbotlib-0.13.dist-info/RECORD
