Metadata-Version: 2.1
Name: ttbotlib
Version: 0.13
Summary: pararam.io bot framework
Author-email: Tamtam team <support@tamtamteam.com>
License: MIT License
Keywords: pararam.io,async,bot
Classifier: Development Status :: 4 - Beta
Classifier: Environment :: Plugins
Classifier: Intended Audience :: Developers
Classifier: License :: OSI Approved :: MIT License
Classifier: Programming Language :: Python
Classifier: Programming Language :: Python :: 3
Classifier: Programming Language :: Python :: 3.10
Classifier: Programming Language :: Python :: 3.11
Classifier: Topic :: Software Development :: Libraries :: Python Modules
Classifier: Framework :: AsyncIO
Requires-Python: >=3.10
License-File: LICENSE.md
Requires-Dist: httpx <1.0
Requires-Dist: uvicorn
Requires-Dist: ttutils
Provides-Extra: dev
Requires-Dist: pytest-runner ; extra == 'dev'
Requires-Dist: pytest ; extra == 'dev'
Requires-Dist: pytest-asyncio ; extra == 'dev'
Requires-Dist: pytest-cov ; extra == 'dev'
Requires-Dist: ruff ; extra == 'dev'
Requires-Dist: mypy ; extra == 'dev'
